libpython/__init__.py
libpython/libpython2.7.so.1.0
libpython/libpython3.6m.a
libpython/libpython3.6m.so.1.0
python_libpython_debian_bin-0.0.5.dist-info/METADATA
python_libpython_debian_bin-0.0.5.dist-info/WHEEL
python_libpython_debian_bin-0.0.5.dist-info/top_level.txt
python_libpython_debian_bin-0.0.5.dist-info/RECORD
